mutesync/__init__.py
mutesync-0.0.2.dist-info/METADATA
mutesync-0.0.2.dist-info/WHEEL
mutesync-0.0.2.dist-info/top_level.txt
mutesync-0.0.2.dist-info/zip-safe
mutesync-0.0.2.dist-info/RECORD
